rest_auth/__init__.py
rest_auth/admin.py
rest_auth/app_settings.py
rest_auth/models.py
rest_auth/serializers.py
rest_auth/social_serializers.py
rest_auth/urls.py
rest_auth/utils.py
rest_auth/views.py
rest_auth/locale/cs/LC_MESSAGES/django.mo
rest_auth/locale/cs/LC_MESSAGES/django.po
rest_auth/locale/de/LC_MESSAGES/django.mo
rest_auth/locale/de/LC_MESSAGES/django.po
rest_auth/locale/es/LC_MESSAGES/django.mo
rest_auth/locale/es/LC_MESSAGES/django.po
rest_auth/locale/fr/LC_MESSAGES/django.mo
rest_auth/locale/fr/LC_MESSAGES/django.po
rest_auth/locale/ko/LC_MESSAGES/django.mo
rest_auth/locale/ko/LC_MESSAGES/django.po
rest_auth/locale/pl/LC_MESSAGES/django.mo
rest_auth/locale/pl/LC_MESSAGES/django.po
rest_auth/locale/pt_BR/LC_MESSAGES/django.po
rest_auth/locale/ru/LC_MESSAGES/django.mo
rest_auth/locale/ru/LC_MESSAGES/django.po
rest_auth/locale/tr/LC_MESSAGES/django.po
rest_auth/locale/zh_Hans/LC_MESSAGES/django.mo
rest_auth/locale/zh_Hans/LC_MESSAGES/django.po
rest_auth/locale/zh_Hant/LC_MESSAGES/django.mo
rest_auth/locale/zh_Hant/LC_MESSAGES/django.po
rest_auth/registration/__init__.py
rest_auth/registration/app_settings.py
rest_auth/registration/serializers.py
rest_auth/registration/urls.py
rest_auth/registration/views.py
rest_auth/tests/__init__.py
rest_auth/tests/django_urls.py
rest_auth/tests/mixins.py
rest_auth/tests/requirements.pip
rest_auth/tests/settings.py
rest_auth/tests/test_api.py
rest_auth/tests/test_social.py
rest_auth/tests/urls.py
django_rest_auth_dj4-0.0.6.dist-info/LICENSE
django_rest_auth_dj4-0.0.6.dist-info/METADATA
django_rest_auth_dj4-0.0.6.dist-info/WHEEL
django_rest_auth_dj4-0.0.6.dist-info/top_level.txt
django_rest_auth_dj4-0.0.6.dist-info/RECORD
