Metadata-Version: 2.1
Name: django-rest-auth-dj4
Version: 0.0.6
Summary: Create a set of REST API endpoints for Authentication and Registration
Home-page: http://github.com/Tivix/django-rest-auth
Author: David Klement
Author-email: david.klement@gmail.com
License: UNKNOWN
Keywords: django rest auth registration rest-framework django-registration api
Platform: UNKNOWN
Classifier: Framework :: Django
Classifier: Intended Audience :: Developers
Classifier: Intended Audience :: System Administrators
Classifier: Operating System :: OS Independent
Classifier: Topic :: Software Development
License-File: LICENSE
Requires-Dist: Django (>=4.0.2)
Requires-Dist: djangorestframework (>=3.13.1)
Requires-Dist: six (>=1.16.0)
Provides-Extra: with_social
Requires-Dist: django-allauth (>=0.49.0) ; extra == 'with_social'
